ai21_tokenizer/__init__.py
ai21_tokenizer/base_jamba_tokenizer.py
ai21_tokenizer/base_tokenizer.py
ai21_tokenizer/file_utils.py
ai21_tokenizer/jamba_tokenizer.py
ai21_tokenizer/resources/j2-tokenizer/config.json
ai21_tokenizer/resources/j2-tokenizer/j2-tokenizer.model
ai21_tokenizer/tokenizer_factory.py
ai21_tokenizer/version.py
ai21_tokenizer-1.1.0.dist-info/LICENSE
ai21_tokenizer-1.1.0.dist-info/METADATA
ai21_tokenizer-1.1.0.dist-info/WHEEL
ai21_tokenizer-1.1.0.dist-info/RECORD
