Metadata-Version: 2.3
Name: ai21-tokenizer
Version: 1.1.0
Summary: 
Author: AI21 Labs
Requires-Python: >=3.8,<4.0
Classifier: Programming Language :: Python :: 3
Classifier: Programming Language :: Python :: 3.8
Classifier: Programming Language :: Python :: 3.9
Classifier: Programming Language :: Python :: 3.10
Classifier: Programming Language :: Python :: 3.11
Classifier: Programming Language :: Python :: 3.12
Classifier: Programming Language :: Python :: 3.13
Requires-Dist: anyio (>=4.4.0,<5.0.0)
Requires-Dist: tokenizers (>=0.15.0,<1.0.0)
